LICENSE
MANIFEST.in
README.rst
setup.cfg
setup.py
_cQuadTree/Point.h
_cQuadTree/QuadTree.h
_cQuadTree/_cQuadTree.cpp
cQuadTree/__init__.py
cQuadTree/metadata.py
cQuadTree/plot.py
cQuadTree/utils.py
cQuadTree.egg-info/PKG-INFO
cQuadTree.egg-info/SOURCES.txt
cQuadTree.egg-info/dependency_links.txt
cQuadTree.egg-info/not-zip-safe
cQuadTree.egg-info/requires.txt
cQuadTree.egg-info/top_level.txt
cQuadTree/tests/__init__.py
cQuadTree/tests/sqrt_tests.py