Metadata-Version: 2.1
Name: cQuadTree
Version: 0.0.2
Summary: Python API to a C++-implementation of a BarnesHutTree/QuadTree
Home-page: https://github.com/benmaier/cQuadTree
Author: Benjamin F. Maier
Author-email: contact@benmaier.org
License: MIT
Project-URL: Documentation, https://github.com/benmaier/cQuadTree
Project-URL: Contributing Statement, https://github.com/benmaier/cQuadTree/blob/master/CONTRIBUTING.md
Project-URL: Bug Reports, https://github.com/benmaier/cQuadTree/issues
Project-URL: Source, https://github.com/benmaier/cQuadTree/
Project-URL: PyPI, https://pypi.org/project/cQuadTree/
Classifier: License :: OSI Approved :: MIT License
Classifier: Programming Language :: Python :: 3.6
Classifier: Programming Language :: Python :: 3.7
Classifier: Programming Language :: Python :: 3.8
License-File: LICENSE
